{"code":0,"msg":"success","data":[{"title":"软件设计中模块划分应遵循的准则是（）。","chooseList":[{"title":"低内聚低耦合","index":0,"selected":false},{"title":"高内聚低耦合","index":1,"selected":false},{"title":"低内聚高耦合","index":2,"selected":false},{"title":"高内聚高耦合","index":3,"selected":false}],"mode":0,"answer":1,"parse":"软件设计中模块划分应遵循的准则是高内聚低耦合、模块大小规模适当、模块的依赖关系适当等。模块的划分应遵循一定的要求，以保证模块划分合理，并进一步保证以此为依据开发出的软件系统可靠性强，易于理解和维护。模块之间的耦合应尽可能的高。故选B。"},{"title":"在数据库设计中，将E-R图转换成关系数据模型的过程属于（）。","chooseList":[{"title":"需求分析阶段","index":0,"selected":false},{"title":"概念设计阶段","index":1,"selected":false},{"title":"逻辑设计阶段","index":2,"selected":false},{"title":"物理设计阶段","index":3,"selected":false}],"mode":0,"answer":2,"parse":"E-R图转换成关系模型数据则是把图形分析出来的联系反映到数据库中，即设计出表，所以属于逻辑设计阶段。故选C。"},{"title":"下列链表中，其逻辑结构属于非线性结构的是（）。","chooseList":[{"title":"二叉链表","index":0,"selected":false},{"title":"循环链表","index":1,"selected":false},{"title":"双向链表","index":2,"selected":false},{"title":"带链的栈","index":3,"selected":false}],"mode":0,"answer":0,"parse":"在定义的链表中，若只含有一个指针域来存放下一个元素地址，称这样的链表为单链表或线性链表。带链的栈可以用来收集计算机存储空间中所有空闲的存储结点，是线性表。在单链表中的结点中增加一个指针域指向它的直接前继，这样的链表，就称为双向链表（一个结点中含有两个指针），也是线性链表。循环链表具有单链表的特征，但又不需要增加额外的存储空间，仅对表的链接方式稍做改变，使得对表的处理更加灵活，属于线性链表。二叉链表是二叉树的物理实现，是一种存储结构，不属于线性结构。故选A。"},{"title":"在 CREATE TABLE 语句中，用来指定外键的关键字是（）。","chooseList":[{"title":"CONSTRAINT","index":0,"selected":false},{"title":"PRIMARY KEY","index":1,"selected":false},{"title":"FOREIGN KEY","index":2,"selected":false},{"title":"CHECK","index":3,"selected":false}],"mode":0,"answer":2,"parse":""},{"title":"MySQL中用来创建数据对象的命令是（）。","chooseList":[{"title":"CREATE","index":0,"selected":false},{"title":"ALTER","index":1,"selected":false},{"title":"DROP","index":2,"selected":false},{"title":"GRANT","index":3,"selected":false}],"mode":0,"answer":0,"parse":""},{"title":"下列关于PRIMARY KEY和UNIQUE的描述中，错误的是（）。","chooseList":[{"title":"两者都要求属性值唯一，故两者的作用完全一样","index":0,"selected":false},{"title":"每个表上只能定义一个PRIMARY KEY约束","index":1,"selected":false},{"title":"每个表上可以定义多个UNIQUE约束","index":2,"selected":false},{"title":"建立UNIQUE约束的属性列上，允许属性值为空","index":3,"selected":false}],"mode":0,"answer":0,"parse":""},{"title":"下列不能使用ALTER命令进行修改的数据库对象是（）。","chooseList":[{"title":"事件","index":0,"selected":false},{"title":"触发器","index":1,"selected":false},{"title":"存储过程","index":2,"selected":false},{"title":"存储函数","index":3,"selected":false}],"mode":0,"answer":1,"parse":""},{"title":"MySQL成功安装后，在系统默认建立的用户个数是（）。","chooseList":[{"title":"0","index":0,"selected":false},{"title":"1","index":1,"selected":false},{"title":"2","index":2,"selected":false},{"title":"3","index":3,"selected":false}],"mode":0,"answer":1,"parse":""},{"title":"结构化程序设计的基本原则不包括（）。","chooseList":[{"title":"模块化","index":0,"selected":false},{"title":"多态性","index":1,"selected":false},{"title":"逐步求精","index":2,"selected":false},{"title":"自顶向下","index":3,"selected":false}],"mode":0,"answer":1,"parse":"结构化程序设计的思想包括：自顶向下、逐步求精、模块化、限制使用goto语句。故选B"},{"title":"下列关于栈的叙述正确的是（）。","chooseList":[{"title":"不能删除数据","index":0,"selected":false},{"title":"只能在栈底插入数据","index":1,"selected":false},{"title":"栈按“先进先出”的组织数据","index":2,"selected":false},{"title":"栈按“先进后出”组织数据","index":3,"selected":false}],"mode":0,"answer":3,"parse":"栈是按“先进后出”的原则组织数据的，数据的插入和删除都在栈顶进行操作。故选D"},{"title":"下列关于数据的描述中，错误的是（）。","chooseList":[{"title":"数据指的就是数字","index":0,"selected":false},{"title":"数据是描述事物的符号记录","index":1,"selected":false},{"title":"数据和它的语义是不可分的","index":2,"selected":false},{"title":"数据是数据库中存储的基本对象","index":3,"selected":false}],"mode":0,"answer":0,"parse":""},{"title":"下列关于SQL的叙述中，正确的是（）。","chooseList":[{"title":"SQL是一种过程化的语言","index":0,"selected":false},{"title":"SQL是关系数据库的通用查询语言","index":1,"selected":false},{"title":"SQL只能以互交方式对数据库进行操作","index":2,"selected":false},{"title":"SQL是专供MySQL使用的结构化查询语言","index":3,"selected":false}],"mode":0,"answer":1,"parse":""},{"title":"给定如下SQL语句：\nCREATE VIEW test.V_test\nAS\nSELECT * FROM test.students\nWHERE age\u003c19;\n该语句的功能是（）。","chooseList":[{"title":"在test表上建立一个名为V_test的视图","index":0,"selected":false},{"title":"在students表上建立一个查询，存储在名为test的表中","index":1,"selected":false},{"title":"在test数据库的students表上建立一个名为V_test的视图","index":2,"selected":false},{"title":"在test表上建立一个名为students的视图","index":3,"selected":false}],"mode":0,"answer":2,"parse":""},{"title":"下列关于MySQL基本表和视图的描述中，正确的是（）。","chooseList":[{"title":"对基本表和视图的操作完全相同","index":0,"selected":false},{"title":"只能对基本表进行查询操作，不能对视图进行查询操作","index":1,"selected":false},{"title":"只能对基本表进行更新操作，不能对视图进行更新操作","index":2,"selected":false},{"title":"能对基本表和视图进行更新操作，但对视图的更新操作是受限制的","index":3,"selected":false}],"mode":0,"answer":3,"parse":""},{"title":"存储过程和存储函数的主要区别在于（）。","chooseList":[{"title":"存储函数可以被其他应用程序调用，而存储过程不能被其他应用程序调用","index":0,"selected":false},{"title":"存储过程中必须包含一条RETURN语句，而存储函数中不允许出现该语句","index":1,"selected":false},{"title":"存储函数只能建立在单个数据表上，而存储过程可以同时建立在多个数据表上","index":2,"selected":false},{"title":"存储过程可以拥有输出参数，而存储函数不能拥有输出参数","index":3,"selected":false}],"mode":0,"answer":3,"parse":""},{"title":"MySQL中，下列关于授权的描述中，正确的是（）。","chooseList":[{"title":"只能对数据表和存储过程授权","index":0,"selected":false},{"title":"只能对数据表和视图授权","index":1,"selected":false},{"title":"可以对数据项、数据表、存储过程和存储函数授权","index":2,"selected":false},{"title":"可以对属性列、数据表、视图、存储过程和存储函数授权","index":3,"selected":false}],"mode":0,"answer":3,"parse":""},{"title":"程序流程图中带有箭头的线段表示的是（）。","chooseList":[{"title":"控制流","index":0,"selected":false},{"title":"数据流","index":1,"selected":false},{"title":"调用关系","index":2,"selected":false},{"title":"图元关系","index":3,"selected":false}],"mode":0,"answer":0,"parse":"在数据流图中，用标有名字的箭头表示数据流。在程序流程图中，用标有名字的箭头表示控制流。故选A。"},{"title":"对长度为n的线性表排序，在最坏情况下，比较次数不是n(n-1)/2的排序方法是（）。","chooseList":[{"title":"堆排序","index":0,"selected":false},{"title":"快速排序","index":1,"selected":false},{"title":"冒泡排序","index":2,"selected":false},{"title":"直接插入排序","index":3,"selected":false}],"mode":0,"answer":0,"parse":"除了推排序算法的比较次数是O(nlog2n)，其他的都是n(n-1)/2。故选A。"},{"title":"数据库管理系统提供的数据控制功能包括（）。","chooseList":[{"title":"数据的完整性","index":0,"selected":false},{"title":"恢复和并发控制","index":1,"selected":false},{"title":"数据的安全性","index":2,"selected":false},{"title":"以上所有各项","index":3,"selected":false}],"mode":0,"answer":3,"parse":""},{"title":"下列关于E-R图向关系模式转换的描述中，正确的是（）。","chooseList":[{"title":"一个实体型通常转换为一个关系模式","index":0,"selected":false},{"title":"一个一对多的联系只能转换为一个独立的关系模式","index":1,"selected":false},{"title":"一个多对多的联系可以与任意一端实体对应的关系合并","index":2,"selected":false},{"title":"三个实体间的一个联系可以转换为一个独立的关系模式","index":3,"selected":false}],"mode":0,"answer":0,"parse":""},{"title":"查询一个表中总记录数的SQL语句语法格式是（）。","chooseList":[{"title":"SELECT COUNT(*) FROM tbl_name;","index":0,"selected":false},{"title":"SELECT COUNT FROM tbl_name;","index":1,"selected":false},{"title":"SELECT FROM COUNT tbl_name;","index":2,"selected":false},{"title":"SELECT * FROM tbl_name;","index":3,"selected":false}],"mode":0,"answer":0,"parse":""},{"title":"在MySQL中，关键字AUTO_INCREMENT用于为列设置自增属性，能够设置该属性的数据类型是（）。","chooseList":[{"title":"字符串类型","index":0,"selected":false},{"title":"日期类型","index":1,"selected":false},{"title":"整型","index":2,"selected":false},{"title":"枚举类型","index":3,"selected":false}],"mode":0,"answer":2,"parse":""},{"title":"使用关键字CALL可以调用的数据库对象是（）。","chooseList":[{"title":"事件","index":0,"selected":false},{"title":"触发器","index":1,"selected":false},{"title":"存储过程","index":2,"selected":false},{"title":"存储函数","index":3,"selected":false}],"mode":0,"answer":2,"parse":""},{"title":"撤销用户的权限应使用的语句是（）。","chooseList":[{"title":"DROP","index":0,"selected":false},{"title":"ALTER","index":1,"selected":false},{"title":"REVOKE","index":2,"selected":false},{"title":"GRANT","index":3,"selected":false}],"mode":0,"answer":2,"parse":""},{"title":"在软件开发中，需求分析阶段产生的主要文档是（）。","chooseList":[{"title":"集成测试计划","index":0,"selected":false},{"title":"概要设计说明书","index":1,"selected":false},{"title":"可行性分析报告","index":2,"selected":false},{"title":"软件需求规格说明书","index":3,"selected":false}],"mode":0,"answer":3,"parse":"集成测试计划是在概要设计阶段编写的文档，A错误。概要设计说明书是总体设计阶段产生的文档，B错误。可行性分析阶段产生可行性分析报告，C错误。故选D。"},{"title":"有三个关系R、S和T如下：[image]由关系R和S通过运算得到关系T，则所使用的运算为（）。","chooseList":[{"title":"并","index":0,"selected":false},{"title":"交","index":1,"selected":false},{"title":"自然连接","index":2,"selected":false},{"title":"笛卡儿积","index":3,"selected":false}],"mode":0,"answer":1,"imageUrl":"https://aivenli.github.io/cputest/mysql/img/cpp_test1_9.png","parse":"自然连接是一种特殊的等值连接，它要求两个关系中进行比较的分量必须是相同的属性组，并且在结果中把重复的属性列去掉；笛卡尔积是用R集合中元素为第一元素，S集合中元素为第二元素构成的有序树；根据关系T可以很明显的看出是从关系R与关系S中取得相同的关系组所以取得是交运算。"},{"title":"下列关于数据库系统三级模式结构的描述中，正确的是（）。","chooseList":[{"title":"一个数据库可以有多个模式","index":0,"selected":false},{"title":"一个数据库可以有多个外模式","index":1,"selected":false},{"title":"一个数据库可以有多个内模式","index":2,"selected":false},{"title":"调用关系一个数据库可以有多个模式和外模式","index":3,"selected":false}],"mode":0,"answer":1,"parse":""},{"title":"如果DELETE语句中没有使用WHERE子句，则下列叙述中正确的是（）。","chooseList":[{"title":"不删除任何记录","index":0,"selected":false},{"title":"删除指定数据表中的全部记录","index":1,"selected":false},{"title":"删除指定数据表中的第一条记录","index":2,"selected":false},{"title":"删除指定数据表中的最后一条记录","index":3,"selected":false}],"mode":0,"answer":1,"parse":""},{"title":"下列关于DROP、TRUNCATE和DELETE命令的描述中，正确的是（）。","chooseList":[{"title":"三者都能删除数据表的结构","index":0,"selected":false},{"title":"三者都只删除数据表中的数据","index":1,"selected":false},{"title":"三者都只删除数据表的结构","index":2,"selected":false},{"title":"三者都能删除数据表中的数据","index":3,"selected":false}],"mode":0,"answer":3,"parse":""},{"title":"MySQL中，激活触发器的命令包括（）。","chooseList":[{"title":"CREATE、DROP、INSERT","index":0,"selected":false},{"title":"SELECT、CREATE、UPDATE","index":1,"selected":false},{"title":"INSERT、DELETE、UPDATE","index":2,"selected":false},{"title":"CREATE、DELETE、UPDATE","index":3,"selected":false}],"mode":0,"answer":2,"parse":""},{"title":"函数NOW()返回的结果是（）。","chooseList":[{"title":"系统的当前日期","index":0,"selected":false},{"title":"系统的当前时间","index":1,"selected":false},{"title":"系统的当前用户","index":2,"selected":false},{"title":"系统的当前日期和时间","index":3,"selected":false}],"mode":0,"answer":3,"parse":""},{"title":"用户LISA在MySQL中建立了一个读者借阅图书数据库，在该数据库中创建了读者表、图书表和借阅表，并为该数据库添加了两个用户U1和U2，给U1授予对所有数据表的查询权限，给U2授予对所有数据表的插入权限，下列用户中不能使用CREATE USER创建用户的是（）。","chooseList":[{"title":"root","index":0,"selected":false},{"title":"LISA","index":1,"selected":false},{"title":"U1","index":2,"selected":false},{"title":"U2","index":3,"selected":false}],"mode":0,"answer":2,"parse":""},{"title":"算法的有穷性是指（）。","chooseList":[{"title":"算法程序的运行时间是有限的","index":0,"selected":false},{"title":"算法程序所处理的数据量是有限的","index":1,"selected":false},{"title":"算法程序的长度是有限的","index":2,"selected":false},{"title":"算法只能被有限的用户使用","index":3,"selected":false}],"mode":0,"answer":0,"parse":"算法原则上能够精确地运行，而且人们用笔和纸做有限次运算后即可完成。有穷性是指算法程序的运行时间是有限的。故选A。"},{"title":"设有表示学生选课的三张表，学生S（学号，姓名，性别，年龄，身份证号），课程C（课号，课名），选课SC（学号，课号，成绩），则表SC的关键字（键或码）为（）。","chooseList":[{"title":"课号，成绩","index":0,"selected":false},{"title":"学号，成绩","index":1,"selected":false},{"title":"学号，课号","index":2,"selected":false},{"title":"学号，姓名，成绩","index":3,"selected":false}],"mode":0,"answer":2,"parse":"学号是学生表S的主键，课号是课程表C的主键，所以选课表SC的关键字就应该是与前两个表能够直接联系且能唯一定义的学号和课号。故选C。"},{"title":"模式/内模式映像保证数据库系统中的数据能够具有较高的（）。","chooseList":[{"title":"逻辑独立性","index":0,"selected":false},{"title":"物理独立性","index":1,"selected":false},{"title":"共享性","index":2,"selected":false},{"title":"结构化","index":3,"selected":false}],"mode":0,"answer":1,"parse":""},{"title":"指定一个数据库为当前数据库的SQL语句语法格式是（）。","chooseList":[{"title":"USE db_name;","index":0,"selected":false},{"title":"SHOW DATABASES;","index":1,"selected":false},{"title":"DROP DATABASE db_name;","index":2,"selected":false},{"title":"CREATE DATABASE db_name;","index":3,"selected":false}],"mode":0,"answer":0,"parse":""},{"title":"下列关于空值的描述中，正确的是（）。","chooseList":[{"title":"空值等同于数值0","index":0,"selected":false},{"title":"空值等同于空字符串","index":1,"selected":false},{"title":"空值表示无值","index":2,"selected":false},{"title":"任意两个空值均相同","index":3,"selected":false}],"mode":0,"answer":2,"parse":""},{"title":"下列关于MySQL触发器的描述中，错误的是（）。","chooseList":[{"title":"触发器的执行是自动的","index":0,"selected":false},{"title":"触发器用来保证数据的完整性","index":1,"selected":false},{"title":"触发器可以创建在表或视图上","index":2,"selected":false},{"title":"一个触发器只能定义在一个基本表上","index":3,"selected":false}],"mode":0,"answer":2,"parse":""},{"title":"在MySQL中执行如下语句：\nSHOW GRANTS FOR \u0027wang\u0027@\u0027localhost\u0027;\n结果显示为：\nGRANT USAGE ON *.* TO \u0027wang\u0027@\u0027localhost\u0027\n该结果显示的是（）。","chooseList":[{"title":"系统中所有的用户信息","index":0,"selected":false},{"title":"用户wang拥有的所有权限","index":1,"selected":false},{"title":"用户名以wang开头的用户拥有的所有权限","index":2,"selected":false},{"title":"系统中所有的资源信息","index":3,"selected":false}],"mode":0,"answer":1,"parse":""},{"title":"备份整个数据库的命令是（）。","chooseList":[{"title":"mysqldump","index":0,"selected":false},{"title":"mysql","index":1,"selected":false},{"title":"mysqlimport","index":2,"selected":false},{"title":"backup","index":3,"selected":false}],"mode":0,"answer":0,"parse":""}]}